progression/__init__.py
progression/decorators.py
progression/progress.py
progression/terminal.py
progression-0.2.0.dist-info/LICENSE
progression-0.2.0.dist-info/METADATA
progression-0.2.0.dist-info/WHEEL
progression-0.2.0.dist-info/RECORD
