Metadata-Version: 2.1
Name: progression
Version: 0.2.0
Summary: advanced progress bar in ASCII art
Home-page: https://github.com/cimatosa/progression
License: BSD (3 clause)
Keywords: progress bar,ascii art,multiprocess
Author: Richard Hartmann
Author-email: richard.hartmann@tu-dresden.de
Requires-Python: >=3.4,<4.0
Classifier: Intended Audience :: Developers
Classifier: License :: OSI Approved :: BSD License
Classifier: License :: Other/Proprietary License
Classifier: Operating System :: Unix
Classifier: Programming Language :: Python :: 3
Classifier: Programming Language :: Python :: 3.4
Classifier: Programming Language :: Python :: 3.5
Classifier: Programming Language :: Python :: 3.6
Classifier: Programming Language :: Python :: 3.7
Classifier: Programming Language :: Python :: 3.8
Classifier: Programming Language :: Python :: 3.9
Classifier: Programming Language :: Python :: 3.10
Classifier: Programming Language :: Python :: 3.11
Classifier: Programming Language :: Python :: 2.7
Classifier: Topic :: Utilities
Requires-Dist: ipython (>=8.14.0,<9.0.0)
Requires-Dist: ipywidgets (>=8.1.0,<9.0.0)
Project-URL: Repository, https://github.com/cimatosa/progression
